tests/test_reset.py
tt_smi/__init__.py
tt_smi/__main__.py
tt_smi/constants.py
tt_smi/log.py
tt_smi/tt_smi.py
tt_smi/tt_smi_backend.py
tt_smi/tt_smi_style.css
tt_smi-3.1.1.dist-info/licenses/LICENSE
tt_smi-3.1.1.dist-info/licenses/LICENSE_understanding.txt
tt_smi-3.1.1.dist-info/METADATA
tt_smi-3.1.1.dist-info/WHEEL
tt_smi-3.1.1.dist-info/entry_points.txt
tt_smi-3.1.1.dist-info/top_level.txt
tt_smi-3.1.1.dist-info/RECORD
