Metadata-Version: 2.4
Name: tt-smi
Version: 3.1.1
Summary: ncurses based hardware monitoring for Tenstorrent silicon
Author-email: Sam Bansal <sbansal@tenstorrent.com>
Maintainer-email: Sam Bansal <sbansal@tenstorrent.com>
License: 
Project-URL: Homepage, http://tenstorrent.com
Project-URL: Bug Reports, https://github.com/tenstorrent/tt-smi/issues
Project-URL: Source, https://github.com/tenstorrent/tt-smi
Classifier: Development Status :: 4 - Beta
Classifier: Environment :: Console :: Curses
Classifier: License :: OSI Approved :: Apache Software License
Classifier: Programming Language :: Python :: 3
Classifier: Programming Language :: Python :: 3.7
Classifier: Programming Language :: Python :: 3.8
Classifier: Programming Language :: Python :: 3.9
Classifier: Programming Language :: Python :: 3.10
Classifier: Programming Language :: Python :: 3.11
Classifier: Programming Language :: Python :: 3 :: Only
Requires-Python: >=3.10
License-File: LICENSE
License-File: LICENSE_understanding.txt
Requires-Dist: distro>=1.8.0
Requires-Dist: elasticsearch>=8.11.0
Requires-Dist: pydantic>=1.2
Requires-Dist: tt_tools_common~=1.6.0
Requires-Dist: pyluwen~=0.8.0
Requires-Dist: rich>=13.7.0
Requires-Dist: textual>=0.59.0
Requires-Dist: pre-commit>=3.5.0
Requires-Dist: tomli
Provides-Extra: dev
Requires-Dist: black==24.10.0; python_version >= "3.9" and extra == "dev"
Requires-Dist: black==24.8.0; python_version == "3.8" and extra == "dev"
Requires-Dist: black==23.3.0; python_version == "3.7" and extra == "dev"
Provides-Extra: test
Requires-Dist: pytest; extra == "test"
Dynamic: license-file
Dynamic: requires-python
